README.md
setup.py
jenkins_rapid/__init__.py
jenkins_rapid/jenkins_debug_console.py
jenkins_rapid.egg-info/PKG-INFO
jenkins_rapid.egg-info/SOURCES.txt
jenkins_rapid.egg-info/dependency_links.txt
jenkins_rapid.egg-info/requires.txt
jenkins_rapid.egg-info/top_level.txt
jenkins_rapid/bin/jrp
jenkins_rapid/data/new_job_template.xml
jenkins_rapid/data/templates/config_xml_parameter_template.yaml