Metadata-Version: 2.1
Name: jenkins-rapid
Version: 0.4.4
Summary: A simple tool to rapidly create and debug jenkins pipelines
Home-page: https://github.com/sidja/jenkins_rapid
Author: Siddarth Vijapurapu
Author-email: sidwho@gmail.com
License: MIT
Platform: UNKNOWN
Classifier: Intended Audience :: Developers
Classifier: Environment :: Console :: Curses
Classifier: Operating System :: POSIX
Classifier: Operating System :: Unix
Classifier: Operating System :: POSIX :: Linux
Classifier: Operating System :: MacOS
Classifier: Natural Language :: English
Classifier: Programming Language :: Python :: 3
Classifier: Programming Language :: Python :: 3.4
Classifier: Programming Language :: Python :: 3.5
Classifier: Programming Language :: Python :: 3.6
Classifier: Programming Language :: Python :: 3.7
Classifier: Programming Language :: Python :: 3.8
Classifier: Topic :: Terminals
